type_info/__init__.py
type_info/_core.py
type_info/_py36_impl.py
type_info/_py37_impl.py
type_info-0.0.2.dist-info/LICENSE
type_info-0.0.2.dist-info/METADATA
type_info-0.0.2.dist-info/WHEEL
type_info-0.0.2.dist-info/top_level.txt
type_info-0.0.2.dist-info/RECORD
